README.rst
setup.cfg
setup.py
dogpile_cache_autoselect/__init__.py
dogpile_cache_autoselect/autoselect.py
dogpile_cache_autoselect.egg-info/PKG-INFO
dogpile_cache_autoselect.egg-info/SOURCES.txt
dogpile_cache_autoselect.egg-info/dependency_links.txt
dogpile_cache_autoselect.egg-info/requires.txt
dogpile_cache_autoselect.egg-info/top_level.txt
dogpile_cache_autoselect.egg-info/zip-safe