Metadata-Version: 1.1
Name: dogpile-cache-autoselect
Version: 1.0
Summary: Simple script that attempts to automatically select an available cache backend for dogpile.cache
Home-page: https://bitbucket.org/mverleg/dogpile.cache.autoselect
Author: (the author)
Author-email: markv.nl.dev@gmail.com
License: Public domain
Keywords: cache
Platform: UNKNOWN
Classifier: Development Status :: 5 - Production/Stable
Classifier: Intended Audience :: Developers
Classifier: Natural Language :: English
Classifier: License :: OSI Approved :: BSD License
Classifier: Operating System :: OS Independent
Classifier: Programming Language :: Python
Classifier: Programming Language :: Python :: 2
Classifier: Programming Language :: Python :: 2.6
Classifier: Programming Language :: Python :: 2.7
Classifier: Programming Language :: Python :: 3
Classifier: Programming Language :: Python :: 3.3
Classifier: Programming Language :: Python :: 3.4
Classifier: Programming Language :: Python :: 3.5
Classifier: Topic :: Software Development :: Libraries :: Python Modules
